Metadata-Version: 1.0
Name: prob-gaussian-and-binomial
Version: 0.1
Summary: Gaussian and Binomial distributions
Home-page: UNKNOWN
Author: Douglas Onkeo
Author-email: douglasonkeo456@gmail.com
License: UNKNOWN
Platform: UNKNOWN
